{
    "IMAGE_INFO": {
        "FILE_NAME": "607559@4_07001_220914_P1_T1.jpg",
        "DATE": "2022-09-14 09:08:28",
        "RESOLUTION": "4032 x 2268",
        "IMAGE_PHOTOGRAPHER": "조정경",
        "FOCUS_DISTANCE": "4.3",
        "EXPOSURE_TIME": "0.00649",
        "SENSITIVITY_ISO": null,
        "PLACE": "주택가분리수거장",
        "REGION_NAME": null,
        "Direction": "4",
        "HEIGHT": null,
        "DAY/NIGHT": "주간",
        "WEATHER": "맑음",
        "IMAGE_HEIGHT": 2268,
        "IMAGE_WIDTH": 4032,
        "IMAGE_SIZE": "4.0 MB"
    },
    "ANNOTATION_INFO": [
        {
            "ID": "1",
            "CLASS": "유리병",
            "DETAILS": "갈색",
            "DAMAGE": "원형",
            "DIRTINESS": "오염없음",
            "COVER": "없음",
            "TRANSPARENCY": "불투명",
            "SHAPE": "유리병형",
            "SHAPE_TYPE": "POLYGON",
            "POINTS": [
                [
                    2044.5794785488447,
                    637.3363265943846
                ],
                [
                    2021.1249271898726,
                    755.4557036763995
                ],
                [
                    1967.1896287594927,
                    927.296073094121
                ],
                [
                    1908.2370932658218,
                    1036.4209792207034
                ],
                [
                    1882.3390837847187,
                    1094.7983086062914
                ],
                [
                    1858.7753954204632,
                    1167.060286256676
                ],
                [
                    1846.6183921849756,
                    1247.2061682250312
                ],
                [
                    1840.2139961359858,
                    1328.8622178496491
                ],
                [
                    1842.6156446543569,
                    1452.1468417927
                ],
                [
                    1844.8350820593844,
                    1701.9068614409819
                ],
                [
                    1843.8559627438287,
                    1792.9649577876578
                ],
                [
                    1843.03269075898,
                    1854.5067107678728
                ],
                [
                    1847.6311703867377,
                    1922.5642092586913
                ],
                [
                    1863.2660011211153,
                    1981.424748493994
                ],
                [
                    1887.1780951854569,
                    2043.9640714315028
                ],
                [
                    1906.466444026128,
                    2078.166618446896
                ],
                [
                    1954.1525637139928,
                    2116.1772935604113
                ],
                [
                    2037.0849457798447,
                    2152.114659122281
                ],
                [
                    2085.462168651592,
                    2161.79010369663
                ],
                [
                    2134.530494707221,
                    2161.79010369663
                ],
                [
                    2188.9940702158915,
                    2146.569840067584
                ],
                [
                    2235.7335672335566,
                    2119.73790659448
                ],
                [
                    2260.4016351039913,
                    2097.2337043267153
                ],
                [
                    2292.7316013263926,
                    2061.674327948505
                ],
                [
                    2316.3419663637455,
                    2026.7406245769118
                ],
                [
                    2331.1185213531094,
                    2008.7517750246432
                ],
                [
                    2346.537535255054,
                    1947.7181783294461
                ],
                [
                    2370.9575486409904,
                    1793.6441499001326
                ],
                [
                    2423.09656997577,
                    1432.7010543147646
                ],
                [
                    2441.1513997797097,
                    1315.13585831121
                ],
                [
                    2444.637601210228,
                    1251.222165418378
                ],
                [
                    2426.044526914131,
                    1144.311988215822
                ],
                [
                    2402.8031840440103,
                    1060.6431538833872
                ],
                [
                    2361.808101118521,
                    954.1364828438125
                ],
                [
                    2344.070567498303,
                    857.2622607641598
                ],
                [
                    2330.894316122171,
                    750.4531141714458
                ],
                [
                    2330.25185720959,
                    626.4585440433084
                ],
                [
                    2333.155162193553,
                    520.2491219800164
                ],
                [
                    2333.810771964362,
                    496.32909762565237
                ],
                [
                    2344.4268392378644,
                    482.831170372975
                ],
                [
                    2355.363310956241,
                    462.3252859010187
                ],
                [
                    2358.553115207434,
                    437.2625382130721
                ],
                [
                    2354.9076246346417,
                    409.46567259553143
                ],
                [
                    2353.0848793482455,
                    390.7825334099712
                ],
                [
                    2348.5280161322553,
                    371.188021581213
                ],
                [
                    2346.705270845859,
                    363.89704043562864
                ],
                [
                    2356.617604690247,
                    355.0215191068517
                ],
                [
                    2364.358316884031,
                    333.7345605739463
                ],
                [
                    2362.9069333476964,
                    313.8989855773754
                ],
                [
                    2357.58519371447,
                    295.9985886292504
                ],
                [
                    2346.9417144480176,
                    281.9685477780173
                ],
                [
                    2329.061711283621,
                    265.8981130182206
                ],
                [
                    2293.463270704128,
                    247.57538624936396
                ],
                [
                    2252.106258854423,
                    235.53473722982957
                ],
                [
                    2217.0313247540403,
                    231.34668539694806
                ],
                [
                    2175.6743129043352,
                    231.87019187605824
                ],
                [
                    2148.4519759906057,
                    235.53473722982957
                ],
                [
                    2117.0415872439935,
                    246.0048668120334
                ],
                [
                    2100.2893799124677,
                    256.9985028733474
                ],
                [
                    2079.2912170784625,
                    271.56584577922166
                ],
                [
                    2068.6198948263836,
                    289.5737020796047
                ],
                [
                    2061.9503184188347,
                    310.2493889430075
                ],
                [
                    2069.286852467139,
                    335.5937792916948
                ],
                [
                    2075.9564288746883,
                    346.9320591845285
                ],
                [
                    2059.94944549657,
                    384.9486447075594
                ],
                [
                    2049.728486738272,
                    412.7942194999965
                ],
                [
                    2048.3363099684093,
                    436.80926878011303
                ],
                [
                    2050.7726193156677,
                    455.25561098078236
                ],
                [
                    2056.689370587581,
                    469.8734670643315
                ],
                [
                    2063.9982986293553,
                    481.35892541569166
                ],
                [
                    2059.829119013114,
                    530.0886763333865
                ]
            ]
        }
    ]
}