{
    "IMAGE_INFO": {
        "FILE_NAME": "1244574@0_01001_221110_P1_T3__3026.jpg",
        "DATE": "2022-11-11 17:05:40",
        "RESOLUTION": "1920 x 1080",
        "IMAGE_PHOTOGRAPHER": "권현진",
        "FOCUS_DISTANCE": "5.6",
        "EXPOSURE_TIME": "1/250",
        "SENSITIVITY_ISO": "2500",
        "PLACE": "강북재활용센터",
        "REGION_NAME": null,
        "Direction": "0",
        "HEIGHT": "100",
        "DAY/NIGHT": "주간",
        "WEATHER": "맑음",
        "IMAGE_HEIGHT": 1080,
        "IMAGE_WIDTH": 1920,
        "IMAGE_SIZE": "522.0 KB"
    },
    "ANNOTATION_INFO": [
        {
            "ID": "1",
            "CLASS": "금속캔",
            "DETAILS": "철캔",
            "DAMAGE": "원형",
            "DIRTINESS": "오염없음",
            "COVER": "없음",
            "TRANSPARENCY": "불투명",
            "SHAPE": "높은 원통형",
            "SHAPE_TYPE": "BOX",
            "POINTS": [
                [
                    712.5466653024508,
                    518.174268793763,
                    424.2323651452281,
                    342.07468879668056
                ]
            ]
        }
    ]
}